aidatafactory/__init__.py
aidatafactory/factory.py
aidatafactory-0.0.3.dist-info/LICENSE
aidatafactory-0.0.3.dist-info/METADATA
aidatafactory-0.0.3.dist-info/WHEEL
aidatafactory-0.0.3.dist-info/top_level.txt
aidatafactory-0.0.3.dist-info/RECORD
