Metadata-Version: 2.1
Name: aidatafactory
Version: 0.0.3
Summary: Data factory for producing synthetic data.
Home-page: UNKNOWN
Author: Ngo Cuong
Author-email: ngo.cuong.work@gmail.com
License: UNKNOWN
Keywords: python,synthetic,data
Platform: UNKNOWN
Classifier: Development Status :: 1 - Planning
Classifier: Intended Audience :: Developers
Classifier: Programming Language :: Python :: 3
Classifier: Operating System :: Unix
Classifier: Operating System :: MacOS :: MacOS X
Classifier: Operating System :: Microsoft :: Windows
Requires-Dist: numpy
Requires-Dist: pandas
Requires-Dist: seaborn
Requires-Dist: tensorflow
Requires-Dist: tensorflow-probability
Requires-Dist: matplotlib
Requires-Dist: scipy
